Activations.py
DataPreProcessing.py
Losses.py
nn.py
optimization.py
save_load.py
visualization.py
nn_for_dummies-0.0.42.dist-info/METADATA
nn_for_dummies-0.0.42.dist-info/WHEEL
nn_for_dummies-0.0.42.dist-info/top_level.txt
nn_for_dummies-0.0.42.dist-info/RECORD
