Metadata-Version: 2.1
Name: nn-for-dummies
Version: 0.0.42
Summary: a small classfication neural network framework
Home-page: UNKNOWN
License: UNKNOWN
Platform: UNKNOWN
Classifier: Programming Language :: Python :: 3
Classifier: Programming Language :: Python :: 3.6
Classifier: Programming Language :: Python :: 3.7
Classifier: Operating System :: OS Independent
